{
  "weapons": [
    {
      "id": 6,
      "itemRarity": 4,
      "itemType": 1,
      "name": "Basic Sword",
      "description": "basic sword",
      "damage": 10,
      "attackSpeed": 1.0,
      "bulletSizeX": 3.0,
      "bulletSizeY": 1.0,
      "bulletSizeZ": 0.0,
      "reloadTime": 0.0,
      "bulletType": "Gun",
      "critical": 0.0,
      "maxBulletAmount": 0,
      "magazineCapacity": 0,
      "cost": 0
    },
    {
      "id": 10,
      "itemRarity": 0,
      "itemType": 1,
      "name": "Basic Gun",
      "description": "A normal gun with decent damage.",
      "damage": 20,
      "attackSpeed": 2.0,
      "bulletSizeX": 4.0,
      "bulletSizeY": 1.5,
      "bulletSizeZ": 0.0,
      "reloadTime": 0.8,
      "bulletType": "Gun",
      "critical": 10.0,
      "maxBulletAmount": 30,
      "magazineCapacity": 5,
      "cost": 10
    },
    {
      "id": 11,
      "itemRarity": 1,
      "itemType": 1,
      "name": "Magnum",
      "description": "A rare shotgun that breathes fire.",
      "damage": 100,
      "attackSpeed": 1.0,
      "bulletSizeX": 4.0,
      "bulletSizeY": 2.0,
      "bulletSizeZ": 0.0,
      "reloadTime": 2.0,
      "bulletType": "Gun",
      "critical": 30.0,
      "maxBulletAmount": 10,
      "magazineCapacity": 3,
      "cost": 30
    },
    {
      "id": 12,
      "itemRarity": 2,
      "itemType": 1,
      "name": "PeoplesGun",
      "description": "An unique machine gun.",
      "damage": 50,
      "attackSpeed": 4.0,
      "bulletSizeX": 4.0,
      "bulletSizeY": 1.5,
      "bulletSizeZ": 0.0,
      "reloadTime": 0.5,
      "bulletType": "Gun",
      "critical": 15.0,
      "maxBulletAmount": 100,
      "magazineCapacity": 20,
      "cost": 50
    },
    {
      "id": 0,
      "itemRarity": 0,
      "itemType": 1,
      "name": "Arrow Shooter",
      "description": "A normal bow that shoots arrows.",
      "damage": 20,
      "attackSpeed": 2.0,
      "bulletSizeX": 4.0,
      "bulletSizeY": 1.0,
      "bulletSizeZ": 0.0,
      "reloadTime": 1.0,
      "bulletType": "Arrow",
      "critical": 20.0,
      "maxBulletAmount": 30,
      "magazineCapacity": 10,
      "cost": 10
    },
    {
      "id": 1,
      "itemRarity": 1,
      "itemType": 1,
      "name": "Silver Arrow Bow",
      "description": "A rare bow with silver arrows for increased damage.",
      "damage": 40,
      "attackSpeed": 2.5,
      "bulletSizeX": 4.0,
      "bulletSizeY": 1.5,
      "bulletSizeZ": 0.5,
      "reloadTime": 0.8,
      "bulletType": "Arrow",
      "critical": 30.0,
      "maxBulletAmount": 50,
      "magazineCapacity": 15,
      "cost": 30
    },
    {
      "id": 2,
      "itemRarity": 2,
      "itemType": 1,
      "name": "Dragon's Arrow Crossbow",
      "description": "An epic crossbow that shoots dragon-infused arrows.",
      "damage": 60,
      "attackSpeed": 3.0,
      "bulletSizeX": 4.0,
      "bulletSizeY": 2.0,
      "bulletSizeZ": 0.0,
      "reloadTime": 1.0,
      "bulletType": "Arrow",
      "critical": 40.0,
      "maxBulletAmount": 70,
      "magazineCapacity": 20,
      "cost": 50
    },
    {
      "id": 3,
      "itemRarity": 0,
      "itemType": 1,
      "name": "Novice Wand",
      "description": "A noraml wand for novice spellcasters.",
      "damage": 20,
      "attackSpeed": 1.0,
      "bulletSizeX": 4.0,
      "bulletSizeY": 1.0,
      "bulletSizeZ": 0.0,
      "reloadTime": 1.5,
      "bulletType": "Wand",
      "critical": 10.0,
      "maxBulletAmount": 15,
      "magazineCapacity": 5,
      "cost": 10
    },
    {
      "id": 4,
      "itemRarity": 1,
      "itemType": 1,
      "name": "Enchanted Crystal Wand",
      "description": "A rare wand with crystals for enhanced magical power.",
      "damage": 50,
      "attackSpeed": 1.2,
      "bulletSizeX": 4.0,
      "bulletSizeY": 1.5,
      "bulletSizeZ": 0.0,
      "reloadTime": 1.2,
      "bulletType": "Wand",
      "critical": 20.0,
      "maxBulletAmount": 20,
      "magazineCapacity": 7,
      "cost": 30
    },
    {
      "id": 5,
      "itemRarity": 2,
      "itemType": 1,
      "name": "Staff of the Archmage",
      "description": "An unique staff wielded by the archmages of old.",
      "damage": 100,
      "attackSpeed": 1.0,
      "bulletSizeX": 4.0,
      "bulletSizeY": 2.0,
      "bulletSizeZ": 0.0,
      "reloadTime": 1.0,
      "bulletType": "Wand",
      "critical": 30.0,
      "maxBulletAmount": 30,
      "magazineCapacity": 10,
      "cost": 50
    },
    {
      "id": 7,
      "itemRarity": 0,
      "itemType": 1,
      "name": "Iron Cannon",
      "description": "A normal cannon for basic firepower.",
      "damage": 60,
      "attackSpeed": 0.8,
      "bulletSizeX": 3.0,
      "bulletSizeY": 1.0,
      "bulletSizeZ": 0.0,
      "reloadTime": 2.0,
      "bulletType": "Cannon",
      "critical": 30.0,
      "maxBulletAmount": 5,
      "magazineCapacity": 2,
      "cost": 10
    },
    {
      "id": 8,
      "itemRarity": 1,
      "itemType": 1,
      "name": "Mithril Cannon",
      "description": "A rare cannon forged from mithril for increased damage.",
      "damage": 90,
      "attackSpeed": 1.0,
      "bulletSizeX": 3.0,
      "bulletSizeY": 1.2,
      "bulletSizeZ": 0.0,
      "reloadTime": 2.0,
      "bulletType": "Cannon",
      "critical": 0.05,
      "maxBulletAmount": 10,
      "magazineCapacity": 3,
      "cost": 30
    },
    {
      "id": 9,
      "itemRarity": 2,
      "itemType": 1,
      "name": "Doomsday Cannon",
      "description": "An unique cannon capable of unleashing devastating blasts.",
      "damage": 120,
      "attackSpeed": 1.2,
      "bulletSizeX": 3.0,
      "bulletSizeY": 1.5,
      "bulletSizeZ": 0.0,
      "reloadTime": 2.0,
      "bulletType": "Cannon",
      "critical": 40.0,
      "maxBulletAmount": 15,
      "magazineCapacity": 5,
      "cost": 50
    }
  ]
}